{"perc": "0.53", "size": 5347, "name": "U.S.", "children": [{"perc": "0.55", "size": 1454, "name": "CO", "children": [{"perc": "0.50", "name": "Arvada", "size": 6}, {"perc": "0.52", "name": "Aurora", "size": 107}, {"perc": "0.58", "name": "Broomfield", "size": 24}, {"perc": "0.50", "name": "Byers", "size": 6}, {"perc": "1.00", "name": "Castle Rock", "size": 3}, {"perc": "0.43", "name": "Centennial", "size": 100}, {"perc": "0.78", "name": "Commerce City", "size": 9}, {"perc": "0.33", "name": "Deer Trail", "size": 3}, {"perc": "0.59", "name": "Denver", "size": 789}, {"perc": "0.51", "name": "Englewood", "size": 272}, {"perc": "0.38", "name": "Golden", "size": 32}, {"perc": "0.33", "name": "Greenwood Village", "size": 15}, {"perc": "0.50", "name": "Henderson", "size": 2}, {"perc": "0.25", "name": "Lakewood", "size": 4}, {"perc": "0.54", "name": "Littleton", "size": 52}, {"perc": "0.50", "name": "Lone Tree", "size": 2}, {"perc": "0.33", "name": "Strasburg", "size": 3}, {"perc": "1.00", "name": "Thornton", "size": 7}, {"perc": "0.43", "name": "Westminster", "size": 7}, {"perc": "0.67", "name": "Wheat Ridge", "size": 3}]}, {"perc": "0.54", "size": 1700, "name": "GA", "children": [{"perc": "0.46", "name": "Alpharetta", "size": 138}, {"perc": "0.50", "name": "Atlanta", "size": 1031}, {"perc": "1.00", "name": "Austell", "size": 3}, {"perc": "0.50", "name": "Chamblee", "size": 2}, {"perc": "0.43", "name": "Conyers", "size": 35}, {"perc": "1.00", "name": "Cumming", "size": 33}, {"perc": "1.00", "name": "Decatur", "size": 3}, {"perc": "1.00", "name": "Douglasville", "size": 25}, {"perc": "0.71", "name": "Duluth", "size": 28}, {"perc": "0.57", "name": "Ellenwood", "size": 7}, {"perc": "1.00", "name": "Fairburn", "size": 8}, {"perc": "0.72", "name": "Fayetteville", "size": 29}, {"perc": "0.50", "name": "Forest Park", "size": 12}, {"perc": "1.00", "name": "Hampton", "size": 8}, {"perc": 0.0, "name": "Johns Creek", "size": 2}, {"perc": "0.35", "name": "Kennesaw", "size": 17}, {"perc": "0.67", "name": "Lawrenceville", "size": 6}, {"perc": "0.38", "name": "Lithia Springs", "size": 52}, {"perc": "1.00", "name": "Locust Grove", "size": 10}, {"perc": "0.56", "name": "Marietta", "size": 36}, {"perc": "1.00", "name": "McDonough", "size": 20}, {"perc": "0.24", "name": "Norcross", "size": 29}, {"perc": "1.00", "name": "Peachtree City", "size": 7}, {"perc": "0.38", "name": "Peachtree Corners", "size": 8}, {"perc": "0.90", "name": "Roswell", "size": 20}, {"perc": "0.44", "name": "Smyrna", "size": 27}, {"perc": "0.88", "name": "Stockbridge", "size": 17}, {"perc": "1.00", "name": "Stone Mountain", "size": 3}, {"perc": "0.46", "name": "Suwanee", "size": 57}, {"perc": "0.60", "name": "Tucker", "size": 5}, {"perc": "1.00", "name": "Tyrone", "size": 5}, {"perc": "1.00", "name": "Union City", "size": 4}, {"perc": "1.00", "name": "Winston", "size": 3}]}, {"perc": "0.51", "size": 2192, "name": "TX", "children": [{"perc": "0.50", "name": "Addison", "size": 2}, {"perc": "0.75", "name": "Aledo", "size": 20}, {"perc": "0.50", "name": "Allen", "size": 18}, {"perc": "0.86", "name": "Anna", "size": 7}, {"perc": "0.33", "name": "Argyle", "size": 3}, {"perc": "0.53", "name": "Arlington", "size": 15}, {"perc": 0.0, "name": "Azle", "size": 2}, {"perc": "1.00", "name": "Bedford", "size": 2}, {"perc": "0.36", "name": "Carrollton", "size": 137}, {"perc": "0.62", "name": "Cedar Hill", "size": 8}, {"perc": "0.67", "name": "Cleburne", "size": 3}, {"perc": "0.88", "name": "Coppell", "size": 34}, {"perc": "0.48", "name": "Dallas", "size": 1066}, {"perc": "0.79", "name": "DeSoto", "size": 19}, {"perc": "1.00", "name": "Decatur", "size": 2}, {"perc": "1.00", "name": "Duncanville", "size": 14}, {"perc": "0.50", "name": "Euless", "size": 4}, {"perc": "0.67", "name": "Farmers Branch", "size": 3}, {"perc": 0.0, "name": "Ferris", "size": 2}, {"perc": "0.46", "name": "Fort Worth", "size": 215}, {"perc": "0.50", "name": "Frisco", "size": 6}, {"perc": "0.62", "name": "Garland", "size": 13}, {"perc": "0.89", "name": "Grand Prairie", "size": 9}, {"perc": "0.43", "name": "Grapevine", "size": 14}, {"perc": "0.50", "name": "Haslet", "size": 4}, {"perc": "1.00", "name": "Heath", "size": 2}, {"perc": "0.62", "name": "Irving", "size": 174}, {"perc": "1.00", "name": "Justin", "size": 2}, {"perc": "0.50", "name": "Keene", "size": 2}, {"perc": "0.47", "name": "Lewisville", "size": 30}, {"perc": "0.50", "name": "McKinney", "size": 2}, {"perc": "0.17", "name": "Melissa", "size": 6}, {"perc": "0.43", "name": "Plano", "size": 138}, {"perc": "1.00", "name": "Princeton", "size": 3}, {"perc": "0.67", "name": "Prosper", "size": 3}, {"perc": "0.83", "name": "Red Oak", "size": 6}, {"perc": "0.48", "name": "Richardson", "size": 135}, {"perc": "1.00", "name": "River Oaks", "size": 2}, {"perc": "0.73", "name": "Roanoke", "size": 15}, {"perc": "0.50", "name": "Rockwall", "size": 2}, {"perc": "1.00", "name": "Sanger", "size": 3}, {"perc": "0.25", "name": "Southlake", "size": 8}, {"perc": "1.00", "name": "Springtown", "size": 2}, {"perc": "0.50", "name": "The Colony", "size": 2}, {"perc": "0.60", "name": "Waxahachie", "size": 5}, {"perc": "1.00", "name": "Weatherford", "size": 3}, {"perc": "0.43", "name": "Westlake", "size": 7}]}]}